ripl/__init__.py
ripl/caption.py
ripl/csv2json.py
ripl/image2exif.py
ripl/imagefind.py
ripl/json2py.py
ripl/md2py.py
ripl/md2slides.py
ripl/py2json.py
ripl/run.py
ripl/runcaption.py
ripl/runner.py
ripl/show.py
ripl/slide2png.py
ripl/slidelayout.py
ripl-0.0.2.dist-info/DESCRIPTION.rst
ripl-0.0.2.dist-info/METADATA
ripl-0.0.2.dist-info/RECORD
ripl-0.0.2.dist-info/WHEEL
ripl-0.0.2.dist-info/dependency_links.txt
ripl-0.0.2.dist-info/entry_points.txt
ripl-0.0.2.dist-info/metadata.json
ripl-0.0.2.dist-info/top_level.txt
