Metadata-Version: 2.0
Name: ripl
Version: 0.0.2
Summary: Really Incredibly Point Less presentation tools
Home-page: https://github.com/openbermuda/ripl
Author: Johnny Gill
Author-email: swfiua@gmail.com
License: GPL v 3
Download-URL: https://github.com/openbermuda/ripl/tarball/0.0.2
Keywords: presentation
Platform: UNKNOWN
Classifier: Development Status :: 3 - Alpha
Classifier: Intended Audience :: End Users/Desktop
Classifier: Programming Language :: Python :: 3
